guriz/__init__.py
guriz/cli.py
guriz/core.py
guriz/repository.py
guriz/SQL/__init__.py
guriz/SQL/config.py
guriz/SQL/connection.py
guriz/SQL/query.py
guriz/documentation/documentate.py
guriz/documentation/registry.py
guriz/documentation/serve_docs.py
guriz/guriz_agent/agent.py
guriz/guriz_agent/context_loader.py
guriz/guriz_agent/toolset.py
guriz/json/form_request.py
guriz/json/form_response.py
guriz-0.4.10.dist-info/METADATA
guriz-0.4.10.dist-info/WHEEL
guriz-0.4.10.dist-info/entry_points.txt
guriz-0.4.10.dist-info/top_level.txt
guriz-0.4.10.dist-info/RECORD
