Metadata-Version: 2.4
Name: guriz
Version: 0.4.10
Requires-Dist: python-dotenv
Requires-Dist: requests
Requires-Dist: fastapi
Requires-Dist: dbutils
Requires-Dist: pytz
Requires-Dist: pymysql
Requires-Dist: rich
Requires-Dist: typer
Requires-Dist: uvicorn
Requires-Dist: agno
Requires-Dist: ollama
